django_data_history/__init__.py
django_data_history/admin.py
django_data_history/apps.py
django_data_history/models.py
django_data_history/tests.py
django_data_history/utils.py
django_data_history/views.py
django_data_history/locale/zh_Hans/LC_MESSAGES/django.mo
django_data_history/locale/zh_Hans/LC_MESSAGES/django.po
django_data_history/migrations/0001_initial.py
django_data_history/migrations/__init__.py
django_data_history/static/django_data_history/css/django_data_history.css
django_data_history/static/django_data_history/js/django_data_history.js
django_data_history/templates/admin/object_history.html
django_data_history/templates/django_data_history/userinfo.html
django_data_history-0.2.0.dist-info/LICENSE
django_data_history-0.2.0.dist-info/METADATA
django_data_history-0.2.0.dist-info/WHEEL
django_data_history-0.2.0.dist-info/top_level.txt
django_data_history-0.2.0.dist-info/RECORD
