Metadata-Version: 2.1
Name: django-data-history
Version: 0.2.0
Summary: A Django application that allows you to store detailed data in the change log and display the detailed information in object's history view.
Author: rRR0VrFP
Maintainer: rRR0VrFP
License: Apache License, Version 2.0
Keywords: django,django data history
Classifier: Development Status :: 5 - Production/Stable
Classifier: Intended Audience :: Developers
Classifier: Topic :: Software Development :: Libraries :: Python Modules
Classifier: License :: OSI Approved :: Apache Software License
Classifier: Programming Language :: Python :: 3
Classifier: Programming Language :: Python :: 3 :: Only
License-File: LICENSE
Requires-Dist: django
Requires-Dist: django-middleware-global-request>=0.3.1
Requires-Dist: django-middleware-request-id>=0.1.2
Requires-Dist: django-static-jquery-ui
Requires-Dist: zenutils
